transformer/.urlignore_example
transformer/__init__.py
transformer/__main__.py
transformer/_version.py
transformer/builders_python.py
transformer/cli.py
transformer/denylist.py
transformer/locust.py
transformer/naming.py
transformer/plugins/__init__.py
transformer/plugins/contracts.py
transformer/plugins/dummy.py
transformer/plugins/resolve.py
transformer/plugins/sanitize_headers.md
transformer/plugins/sanitize_headers.py
transformer/python.py
transformer/request.py
transformer/scenario.py
transformer/task.py
transformer/transform.py
har_transformer-2.0.0.dist-info/entry_points.txt
har_transformer-2.0.0.dist-info/LICENSE
har_transformer-2.0.0.dist-info/WHEEL
har_transformer-2.0.0.dist-info/METADATA
har_transformer-2.0.0.dist-info/RECORD
